{
  "recording_timestamp": 1757346660.6979902,
  "elapsed_time_s": 5.0,
  "fz": 0.974587,
  "peak_intensity": 0.136,
  "deformation_mesh": [
    {
      "coordinates": [
        0,
        0
      ],
      "magnitude": 2.191859483718872,
      "direction": [
        -0.02376589924097061,
        -0.9997175335884094
      ]
    },
    {
      "coordinates": [
        22,
        0
      ],
      "magnitude": 2.2707531452178955,
      "direction": [
        0.10768752545118332,
        -0.9941848516464233
      ]
    },
    {
      "coordinates": [
        45,
        0
      ],
      "magnitude": 2.4457366466522217,
      "direction": [
        0.07412651926279068,
        -0.9972488284111023
      ]
    },
    {
      "coordinates": [
        68,
        0
      ],
      "magnitude": 2.8744537830352783,
      "direction": [
        0.16860634088516235,
        -0.9856834411621094
      ]
    },
    {
      "coordinates": [
        91,
        0
      ],
      "magnitude": 2.572209358215332,
      "direction": [
        0.25737398862838745,
        -0.9663118720054626
      ]
    },
    {
      "coordinates": [
        113,
        0
      ],
      "magnitude": 2.7493457794189453,
      "direction": [
        0.5311623811721802,
        -0.8472700715065002
      ]
    },
    {
      "coordinates": [
        136,
        0
      ],
      "magnitude": 3.0127077102661133,
      "direction": [
        0.5352858304977417,
        -0.8446709513664246
      ]
    },
    {
      "coordinates": [
        159,
        0
      ],
      "magnitude": 2.8218982219696045,
      "direction": [
        0.5494365692138672,
        -0.8355353474617004
      ]
    },
    {
      "coordinates": [
        182,
        0
      ],
      "magnitude": 2.427056074142456,
      "direction": [
        0.7304033637046814,
        -0.6830160021781921
      ]
    },
    {
      "coordinates": [
        205,
        0
      ],
      "magnitude": 2.758296012878418,
      "direction": [
        0.6671627759933472,
        -0.7449119091033936
      ]
    },
    {
      "coordinates": [
        227,
        0
      ],
      "magnitude": 2.872156858444214,
      "direction": [
        0.6857873797416687,
        -0.7278018593788147
      ]
    },
    {
      "coordinates": [
        250,
        0
      ],
      "magnitude": 2.9603376388549805,
      "direction": [
        0.8068913817405701,
        -0.5906998515129089
      ]
    },
    {
      "coordinates": [
        273,
        0
      ],
      "magnitude": 3.1330697536468506,
      "direction": [
        0.8230767250061035,
        -0.5679302215576172
      ]
    },
    {
      "coordinates": [
        296,
        0
      ],
      "magnitude": 3.2214653491973877,
      "direction": [
        0.8560880422592163,
        -0.5168299674987793
      ]
    },
    {
      "coordinates": [
        319,
        0
      ],
      "magnitude": 2.9632482528686523,
      "direction": [
        0.8555564880371094,
        -0.5177093744277954
      ]
    },
    {
      "coordinates": [
        0,
        17
      ],
      "magnitude": 2.282982587814331,
      "direction": [
        -0.2125571072101593,
        -0.9771485924720764
      ]
    },
    {
      "coordinates": [
        22,
        17
      ],
      "magnitude": 2.3875370025634766,
      "direction": [
        -0.026194006204605103,
        -0.9996568560600281
      ]
    },
    {
      "coordinates": [
        45,
        17
      ],
      "magnitude": 2.4096784591674805,
      "direction": [
        0.014079082757234573,
        -0.9999008774757385
      ]
    },
    {
      "coordinates": [
        68,
        17
      ],
      "magnitude": 2.835754156112671,
      "direction": [
        0.16692803800106049,
        -0.985969066619873
      ]
    },
    {
      "coordinates": [
        91,
        17
      ],
      "magnitude": 3.1036317348480225,
      "direction": [
        0.290461927652359,
        -0.9568865299224854
      ]
    },
    {
      "coordinates": [
        113,
        17
      ],
      "magnitude": 2.73730731010437,
      "direction": [
        0.4317163825035095,
        -0.9020093679428101
      ]
    },
    {
      "coordinates": [
        136,
        17
      ],
      "magnitude": 2.6804616451263428,
      "direction": [
        0.46007829904556274,
        -0.8878783583641052
      ]
    },
    {
      "coordinates": [
        159,
        17
      ],
      "magnitude": 2.7139835357666016,
      "direction": [
        0.5631440877914429,
        -0.8263587355613708
      ]
    },
    {
      "coordinates": [
        182,
        17
      ],
      "magnitude": 2.288362979888916,
      "direction": [
        0.7422648072242737,
        -0.6701067090034485
      ]
    },
    {
      "coordinates": [
        205,
        17
      ],
      "magnitude": 2.732398271560669,
      "direction": [
        0.7558045387268066,
        -0.6547973155975342
      ]
    },
    {
      "coordinates": [
        227,
        17
      ],
      "magnitude": 3.0261881351470947,
      "direction": [
        0.7649862766265869,
        -0.6440464854240417
      ]
    },
    {
      "coordinates": [
        250,
        17
      ],
      "magnitude": 2.9191973209381104,
      "direction": [
        0.7976972460746765,
        -0.6030581593513489
      ]
    },
    {
      "coordinates": [
        273,
        17
      ],
      "magnitude": 3.18843412399292,
      "direction": [
        0.8287039995193481,
        -0.559687077999115
      ]
    },
    {
      "coordinates": [
        296,
        17
      ],
      "magnitude": 3.292980909347534,
      "direction": [
        0.8347607851028442,
        -0.5506128072738647
      ]
    },
    {
      "coordinates": [
        319,
        17
      ],
      "magnitude": 3.2564847469329834,
      "direction": [
        0.9009796380996704,
        -0.4338614046573639
      ]
    },
    {
      "coordinates": [
        0,
        34
      ],
      "magnitude": 2.5914905071258545,
      "direction": [
        -0.27394813299179077,
        -0.961744487285614
      ]
    },
    {
      "coordinates": [
        22,
        34
      ],
      "magnitude": 2.577226400375366,
      "direction": [
        -0.26645615696907043,
        -0.9638469815254211
      ]
    },
    {
      "coordinates": [
        45,
        34
      ],
      "magnitude": 2.787803888320923,
      "direction": [
        0.09164523333311081,
        -0.9957917332649231
      ]
    },
    {
      "coordinates": [
        68,
        34
      ],
      "magnitude": 2.7931010723114014,
      "direction": [
        0.1723526120185852,
        -0.9850353002548218
      ]
    },
    {
      "coordinates": [
        91,
        34
      ],
      "magnitude": 3.3707892894744873,
      "direction": [
        0.34972336888313293,
        -0.9368530511856079
      ]
    },
    {
      "coordinates": [
        113,
        34
      ],
      "magnitude": 3.04603910446167,
      "direction": [
        0.44833505153656006,
        -0.8938655853271484
      ]
    },
    {
      "coordinates": [
        136,
        34
      ],
      "magnitude": 3.052523612976074,
      "direction": [
        0.6174526810646057,
        -0.7866079807281494
      ]
    },
    {
      "coordinates": [
        159,
        34
      ],
      "magnitude": 2.763035774230957,
      "direction": [
        0.6695970296859741,
        -0.742724597454071
      ]
    },
    {
      "coordinates": [
        182,
        34
      ],
      "magnitude": 2.709455728530884,
      "direction": [
        0.7242826819419861,
        -0.6895031332969666
      ]
    },
    {
      "coordinates": [
        205,
        34
      ],
      "magnitude": 2.9968271255493164,
      "direction": [
        0.7343345284461975,
        -0.6787877082824707
      ]
    },
    {
      "coordinates": [
        227,
        34
      ],
      "magnitude": 3.0940587520599365,
      "direction": [
        0.7774210572242737,
        -0.6289805769920349
      ]
    },
    {
      "coordinates": [
        250,
        34
      ],
      "magnitude": 2.957566261291504,
      "direction": [
        0.8272958397865295,
        -0.561766505241394
      ]
    },
    {
      "coordinates": [
        273,
        34
      ],
      "magnitude": 3.147336959838867,
      "direction": [
        0.802324652671814,
        -0.5968878269195557
      ]
    },
    {
      "coordinates": [
        296,
        34
      ],
      "magnitude": 3.6043083667755127,
      "direction": [
        0.8311769962310791,
        -0.5560079216957092
      ]
    },
    {
      "coordinates": [
        319,
        34
      ],
      "magnitude": 3.2947983741760254,
      "direction": [
        0.8770408630371094,
        -0.48041588068008423
      ]
    },
    {
      "coordinates": [
        0,
        51
      ],
      "magnitude": 2.4028544425964355,
      "direction": [
        -0.31575074791908264,
        -0.9488421678543091
      ]
    },
    {
      "coordinates": [
        22,
        51
      ],
      "magnitude": 2.8470990657806396,
      "direction": [
        -0.29871711134910583,
        -0.9543417096138
      ]
    },
    {
      "coordinates": [
        45,
        51
      ],
      "magnitude": 2.7827656269073486,
      "direction": [
        -0.07736831158399582,
        -0.9970026016235352
      ]
    },
    {
      "coordinates": [
        68,
        51
      ],
      "magnitude": 2.7876741886138916,
      "direction": [
        0.019190160557627678,
        -0.9998158812522888
      ]
    },
    {
      "coordinates": [
        91,
        51
      ],
      "magnitude": 3.315321922302246,
      "direction": [
        0.17847885191440582,
        -0.9839437007904053
      ]
    },
    {
      "coordinates": [
        113,
        51
      ],
      "magnitude": 3.2822866439819336,
      "direction": [
        0.38747337460517883,
        -0.9218809604644775
      ]
    },
    {
      "coordinates": [
        136,
        51
      ],
      "magnitude": 3.46694278717041,
      "direction": [
        0.6161461472511292,
        -0.7876317501068115
      ]
    },
    {
      "coordinates": [
        159,
        51
      ],
      "magnitude": 3.4788107872009277,
      "direction": [
        0.6489890217781067,
        -0.7607977986335754
      ]
    },
    {
      "coordinates": [
        182,
        51
      ],
      "magnitude": 3.1198720932006836,
      "direction": [
        0.7465787529945374,
        -0.6652970314025879
      ]
    },
    {
      "coordinates": [
        205,
        51
      ],
      "magnitude": 3.277726888656616,
      "direction": [
        0.7271143794059753,
        -0.6865163445472717
      ]
    },
    {
      "coordinates": [
        227,
        51
      ],
      "magnitude": 3.2817671298980713,
      "direction": [
        0.7544052004814148,
        -0.6564090251922607
      ]
    },
    {
      "coordinates": [
        250,
        51
      ],
      "magnitude": 3.409672498703003,
      "direction": [
        0.8514847159385681,
        -0.5243793725967407
      ]
    },
    {
      "coordinates": [
        273,
        51
      ],
      "magnitude": 3.523671865463257,
      "direction": [
        0.8434135317802429,
        -0.537264883518219
      ]
    },
    {
      "coordinates": [
        296,
        51
      ],
      "magnitude": 3.709285020828247,
      "direction": [
        0.8353291749954224,
        -0.549750030040741
      ]
    },
    {
      "coordinates": [
        319,
        51
      ],
      "magnitude": 3.761256694793701,
      "direction": [
        0.8993175029754639,
        -0.4372963011264801
      ]
    },
    {
      "coordinates": [
        0,
        68
      ],
      "magnitude": 2.8815674781799316,
      "direction": [
        -0.5687702298164368,
        -0.8224963545799255
      ]
    },
    {
      "coordinates": [
        22,
        68
      ],
      "magnitude": 3.285834789276123,
      "direction": [
        -0.4477602243423462,
        -0.8941536545753479
      ]
    },
    {
      "coordinates": [
        45,
        68
      ],
      "magnitude": 3.260420560836792,
      "direction": [
        -0.3210524320602417,
        -0.9470614790916443
      ]
    },
    {
      "coordinates": [
        68,
        68
      ],
      "magnitude": 3.625271797180176,
      "direction": [
        -0.19488124549388885,
        -0.9808268547058105
      ]
    },
    {
      "coordinates": [
        91,
        68
      ],
      "magnitude": 3.6644399166107178,
      "direction": [
        0.04515272378921509,
        -0.9989801049232483
      ]
    },
    {
      "coordinates": [
        113,
        68
      ],
      "magnitude": 3.8907458782196045,
      "direction": [
        0.29320213198661804,
        -0.956050455570221
      ]
    },
    {
      "coordinates": [
        136,
        68
      ],
      "magnitude": 3.7239248752593994,
      "direction": [
        0.49341291189193726,
        -0.8697951436042786
      ]
    },
    {
      "coordinates": [
        159,
        68
      ],
      "magnitude": 3.5708799362182617,
      "direction": [
        0.5944662690162659,
        -0.8041205406188965
      ]
    },
    {
      "coordinates": [
        182,
        68
      ],
      "magnitude": 3.592978000640869,
      "direction": [
        0.7302904725074768,
        -0.6831367015838623
      ]
    },
    {
      "coordinates": [
        205,
        68
      ],
      "magnitude": 3.674696207046509,
      "direction": [
        0.7915318012237549,
        -0.6111279726028442
      ]
    },
    {
      "coordinates": [
        227,
        68
      ],
      "magnitude": 3.9766428470611572,
      "direction": [
        0.7704550623893738,
        -0.6374942660331726
      ]
    },
    {
      "coordinates": [
        250,
        68
      ],
      "magnitude": 4.111303806304932,
      "direction": [
        0.833730161190033,
        -0.5521722435951233
      ]
    },
    {
      "coordinates": [
        273,
        68
      ],
      "magnitude": 3.845088005065918,
      "direction": [
        0.8541409373283386,
        -0.5200414657592773
      ]
    },
    {
      "coordinates": [
        296,
        68
      ],
      "magnitude": 3.755391836166382,
      "direction": [
        0.854035496711731,
        -0.5202147364616394
      ]
    },
    {
      "coordinates": [
        319,
        68
      ],
      "magnitude": 3.946068525314331,
      "direction": [
        0.8841060400009155,
        -0.46728619933128357
      ]
    },
    {
      "coordinates": [
        0,
        85
      ],
      "magnitude": 3.374824047088623,
      "direction": [
        -0.6913127899169922,
        -0.7225555777549744
      ]
    },
    {
      "coordinates": [
        22,
        85
      ],
      "magnitude": 3.9807989597320557,
      "direction": [
        -0.6246320605278015,
        -0.7809191346168518
      ]
    },
    {
      "coordinates": [
        45,
        85
      ],
      "magnitude": 4.111285209655762,
      "direction": [
        -0.47958341240882874,
        -0.8774963021278381
      ]
    },
    {
      "coordinates": [
        68,
        85
      ],
      "magnitude": 3.937370777130127,
      "direction": [
        -0.26973089575767517,
        -0.962935745716095
      ]
    },
    {
      "coordinates": [
        91,
        85
      ],
      "magnitude": 4.0778632164001465,
      "direction": [
        -0.062328822910785675,
        -0.998055636882782
      ]
    },
    {
      "coordinates": [
        113,
        85
      ],
      "magnitude": 4.003226280212402,
      "direction": [
        0.28424641489982605,
        -0.9587512016296387
      ]
    },
    {
      "coordinates": [
        136,
        85
      ],
      "magnitude": 3.8071279525756836,
      "direction": [
        0.445518434047699,
        -0.8952727317810059
      ]
    },
    {
      "coordinates": [
        159,
        85
      ],
      "magnitude": 3.646416425704956,
      "direction": [
        0.6023558974266052,
        -0.7982276082038879
      ]
    },
    {
      "coordinates": [
        182,
        85
      ],
      "magnitude": 3.7591025829315186,
      "direction": [
        0.7967306971549988,
        -0.6043344736099243
      ]
    },
    {
      "coordinates": [
        205,
        85
      ],
      "magnitude": 4.079944133758545,
      "direction": [
        0.8112537860870361,
        -0.5846940279006958
      ]
    },
    {
      "coordinates": [
        227,
        85
      ],
      "magnitude": 4.52765417098999,
      "direction": [
        0.820629894733429,
        -0.5714600086212158
      ]
    },
    {
      "coordinates": [
        250,
        85
      ],
      "magnitude": 4.7588090896606445,
      "direction": [
        0.8374341130256653,
        -0.546538233757019
      ]
    },
    {
      "coordinates": [
        273,
        85
      ],
      "magnitude": 4.053555488586426,
      "direction": [
        0.9278895854949951,
        -0.37285512685775757
      ]
    },
    {
      "coordinates": [
        296,
        85
      ],
      "magnitude": 4.318606376647949,
      "direction": [
        0.9007480144500732,
        -0.4343421161174774
      ]
    },
    {
      "coordinates": [
        319,
        85
      ],
      "magnitude": 4.458859920501709,
      "direction": [
        0.9118983745574951,
        -0.4104159474372864
      ]
    },
    {
      "coordinates": [
        0,
        102
      ],
      "magnitude": 3.9425761699676514,
      "direction": [
        -0.8722602128982544,
        -0.4890419542789459
      ]
    },
    {
      "coordinates": [
        22,
        102
      ],
      "magnitude": 4.9314165115356445,
      "direction": [
        -0.7603586316108704,
        -0.6495034694671631
      ]
    },
    {
      "coordinates": [
        45,
        102
      ],
      "magnitude": 4.579006671905518,
      "direction": [
        -0.6628333926200867,
        -0.7487670183181763
      ]
    },
    {
      "coordinates": [
        68,
        102
      ],
      "magnitude": 4.003742694854736,
      "direction": [
        -0.40052831172943115,
        -0.916284441947937
      ]
    },
    {
      "coordinates": [
        91,
        102
      ],
      "magnitude": 3.708881378173828,
      "direction": [
        -0.12047256529331207,
        -0.9927166700363159
      ]
    },
    {
      "coordinates": [
        113,
        102
      ],
      "magnitude": 3.630474090576172,
      "direction": [
        0.29634320735931396,
        -0.9550815224647522
      ]
    },
    {
      "coordinates": [
        136,
        102
      ],
      "magnitude": 3.7403805255889893,
      "direction": [
        0.4725339114665985,
        -0.8813124299049377
      ]
    },
    {
      "coordinates": [
        159,
        102
      ],
      "magnitude": 3.6549723148345947,
      "direction": [
        0.6188046932220459,
        -0.7855448722839355
      ]
    },
    {
      "coordinates": [
        182,
        102
      ],
      "magnitude": 4.042243003845215,
      "direction": [
        0.8817558288574219,
        -0.47170594334602356
      ]
    },
    {
      "coordinates": [
        205,
        102
      ],
      "magnitude": 4.468207359313965,
      "direction": [
        0.8655716180801392,
        -0.500785231590271
      ]
    },
    {
      "coordinates": [
        227,
        102
      ],
      "magnitude": 5.032928466796875,
      "direction": [
        0.8373790979385376,
        -0.5466225743293762
      ]
    },
    {
      "coordinates": [
        250,
        102
      ],
      "magnitude": 5.064736843109131,
      "direction": [
        0.8540288209915161,
        -0.5202255845069885
      ]
    },
    {
      "coordinates": [
        273,
        102
      ],
      "magnitude": 4.965460300445557,
      "direction": [
        0.9120619893074036,
        -0.41005226969718933
      ]
    },
    {
      "coordinates": [
        296,
        102
      ],
      "magnitude": 4.72295618057251,
      "direction": [
        0.932327389717102,
        -0.3616154193878174
      ]
    },
    {
      "coordinates": [
        319,
        102
      ],
      "magnitude": 4.632379055023193,
      "direction": [
        0.942670464515686,
        -0.33372485637664795
      ]
    },
    {
      "coordinates": [
        0,
        119
      ],
      "magnitude": 4.533225059509277,
      "direction": [
        -0.8881509900093079,
        -0.45955169200897217
      ]
    },
    {
      "coordinates": [
        22,
        119
      ],
      "magnitude": 4.596532344818115,
      "direction": [
        -0.8880943059921265,
        -0.45966124534606934
      ]
    },
    {
      "coordinates": [
        45,
        119
      ],
      "magnitude": 4.573604106903076,
      "direction": [
        -0.7914466857910156,
        -0.6112381219863892
      ]
    },
    {
      "coordinates": [
        68,
        119
      ],
      "magnitude": 3.8287417888641357,
      "direction": [
        -0.6375613212585449,
        -0.7703995704650879
      ]
    },
    {
      "coordinates": [
        91,
        119
      ],
      "magnitude": 2.975898504257202,
      "direction": [
        -0.25292426347732544,
        -0.9674860835075378
      ]
    },
    {
      "coordinates": [
        113,
        119
      ],
      "magnitude": 2.85727858543396,
      "direction": [
        0.1928119659423828,
        -0.9812358021736145
      ]
    },
    {
      "coordinates": [
        136,
        119
      ],
      "magnitude": 3.2735679149627686,
      "direction": [
        0.5204907655715942,
        -0.8538673520088196
      ]
    },
    {
      "coordinates": [
        159,
        119
      ],
      "magnitude": 3.1586337089538574,
      "direction": [
        0.8204019069671631,
        -0.5717872977256775
      ]
    },
    {
      "coordinates": [
        182,
        119
      ],
      "magnitude": 3.991258144378662,
      "direction": [
        0.9674450159072876,
        -0.25308123230934143
      ]
    },
    {
      "coordinates": [
        205,
        119
      ],
      "magnitude": 4.672119140625,
      "direction": [
        0.951417863368988,
        -0.3079029321670532
      ]
    },
    {
      "coordinates": [
        227,
        119
      ],
      "magnitude": 5.168525218963623,
      "direction": [
        0.9095416069030762,
        -0.4156128764152527
      ]
    },
    {
      "coordinates": [
        250,
        119
      ],
      "magnitude": 5.602904796600342,
      "direction": [
        0.9055767059326172,
        -0.4241824150085449
      ]
    },
    {
      "coordinates": [
        273,
        119
      ],
      "magnitude": 5.405872344970703,
      "direction": [
        0.9259466528892517,
        -0.3776543438434601
      ]
    },
    {
      "coordinates": [
        296,
        119
      ],
      "magnitude": 5.2155866622924805,
      "direction": [
        0.9528658986091614,
        -0.30339184403419495
      ]
    },
    {
      "coordinates": [
        319,
        119
      ],
      "magnitude": 4.749317169189453,
      "direction": [
        0.9670462012290955,
        -0.25460097193717957
      ]
    },
    {
      "coordinates": [
        0,
        136
      ],
      "magnitude": 5.027432918548584,
      "direction": [
        -0.9406837821006775,
        -0.33928442001342773
      ]
    },
    {
      "coordinates": [
        22,
        136
      ],
      "magnitude": 5.121459484100342,
      "direction": [
        -0.9589861631393433,
        -0.2834528982639313
      ]
    },
    {
      "coordinates": [
        45,
        136
      ],
      "magnitude": 4.4058966636657715,
      "direction": [
        -0.9570237994194031,
        -0.2900094985961914
      ]
    },
    {
      "coordinates": [
        68,
        136
      ],
      "magnitude": 3.0782811641693115,
      "direction": [
        -0.809292733669281,
        -0.5874055624008179
      ]
    },
    {
      "coordinates": [
        91,
        136
      ],
      "magnitude": 2.433469772338867,
      "direction": [
        -0.23329699039459229,
        -0.9724054932594299
      ]
    },
    {
      "coordinates": [
        113,
        136
      ],
      "magnitude": 2.119004726409912,
      "direction": [
        0.11609440296888351,
        -0.9932382106781006
      ]
    },
    {
      "coordinates": [
        136,
        136
      ],
      "magnitude": 2.5991132259368896,
      "direction": [
        0.822191059589386,
        -0.5692116022109985
      ]
    },
    {
      "coordinates": [
        159,
        136
      ],
      "magnitude": 3.2614033222198486,
      "direction": [
        0.9877877831459045,
        -0.15580551326274872
      ]
    },
    {
      "coordinates": [
        182,
        136
      ],
      "magnitude": 4.109802722930908,
      "direction": [
        0.9997720122337341,
        -0.021353380754590034
      ]
    },
    {
      "coordinates": [
        205,
        136
      ],
      "magnitude": 4.721858024597168,
      "direction": [
        0.97597736120224,
        -0.21787205338478088
      ]
    },
    {
      "coordinates": [
        227,
        136
      ],
      "magnitude": 5.333324909210205,
      "direction": [
        0.9634526968002319,
        -0.26787859201431274
      ]
    },
    {
      "coordinates": [
        250,
        136
      ],
      "magnitude": 5.840176105499268,
      "direction": [
        0.9623174667358398,
        -0.27192848920822144
      ]
    },
    {
      "coordinates": [
        273,
        136
      ],
      "magnitude": 6.057301998138428,
      "direction": [
        0.9663615226745605,
        -0.2571876049041748
      ]
    },
    {
      "coordinates": [
        296,
        136
      ],
      "magnitude": 5.50299596786499,
      "direction": [
        0.972464382648468,
        -0.233051598072052
      ]
    },
    {
      "coordinates": [
        319,
        136
      ],
      "magnitude": 5.091006278991699,
      "direction": [
        0.9901373386383057,
        -0.14010046422481537
      ]
    },
    {
      "coordinates": [
        0,
        153
      ],
      "magnitude": 5.286900997161865,
      "direction": [
        -0.9932325482368469,
        -0.11614276468753815
      ]
    },
    {
      "coordinates": [
        22,
        153
      ],
      "magnitude": 5.329440593719482,
      "direction": [
        -0.9897477030754089,
        -0.14282658696174622
      ]
    },
    {
      "coordinates": [
        45,
        153
      ],
      "magnitude": 4.877723693847656,
      "direction": [
        -0.9977759122848511,
        -0.06665699928998947
      ]
    },
    {
      "coordinates": [
        68,
        153
      ],
      "magnitude": 2.7650856971740723,
      "direction": [
        -0.9965637922286987,
        -0.08282932639122009
      ]
    },
    {
      "coordinates": [
        91,
        153
      ],
      "magnitude": 1.642104983329773,
      "direction": [
        -0.8274627923965454,
        -0.5615205764770508
      ]
    },
    {
      "coordinates": [
        113,
        153
      ],
      "magnitude": 0.9126058220863342,
      "direction": [
        0.32780900597572327,
        -0.9447439908981323
      ]
    },
    {
      "coordinates": [
        136,
        153
      ],
      "magnitude": 2.283165693283081,
      "direction": [
        0.9868234992027283,
        -0.1618003249168396
      ]
    },
    {
      "coordinates": [
        159,
        153
      ],
      "magnitude": 3.3436551094055176,
      "direction": [
        0.9672040939331055,
        0.2540004551410675
      ]
    },
    {
      "coordinates": [
        182,
        153
      ],
      "magnitude": 4.391576290130615,
      "direction": [
        0.9545309543609619,
        0.29811179637908936
      ]
    },
    {
      "coordinates": [
        205,
        153
      ],
      "magnitude": 5.082492351531982,
      "direction": [
        0.9970030188560486,
        0.07736308127641678
      ]
    },
    {
      "coordinates": [
        227,
        153
      ],
      "magnitude": 5.545233726501465,
      "direction": [
        0.9944184422492981,
        -0.10550791025161743
      ]
    },
    {
      "coordinates": [
        250,
        153
      ],
      "magnitude": 6.500270366668701,
      "direction": [
        0.9896174073219299,
        -0.14372649788856506
      ]
    },
    {
      "coordinates": [
        273,
        153
      ],
      "magnitude": 6.456201076507568,
      "direction": [
        0.9839015603065491,
        -0.17871131002902985
      ]
    },
    {
      "coordinates": [
        296,
        153
      ],
      "magnitude": 6.1337761878967285,
      "direction": [
        0.9943490028381348,
        -0.10616046190261841
      ]
    },
    {
      "coordinates": [
        319,
        153
      ],
      "magnitude": 5.460322856903076,
      "direction": [
        0.9985705614089966,
        -0.053449083119630814
      ]
    },
    {
      "coordinates": [
        0,
        170
      ],
      "magnitude": 6.007753849029541,
      "direction": [
        -0.9707391858100891,
        0.24013639986515045
      ]
    },
    {
      "coordinates": [
        22,
        170
      ],
      "magnitude": 5.971644878387451,
      "direction": [
        -0.9796655774116516,
        0.20063751935958862
      ]
    },
    {
      "coordinates": [
        45,
        170
      ],
      "magnitude": 5.1243367195129395,
      "direction": [
        -0.9596856236457825,
        0.28107547760009766
      ]
    },
    {
      "coordinates": [
        68,
        170
      ],
      "magnitude": 3.0046229362487793,
      "direction": [
        -0.9398680329322815,
        0.3415376543998718
      ]
    },
    {
      "coordinates": [
        91,
        170
      ],
      "magnitude": 1.8962295055389404,
      "direction": [
        -0.8968670964241028,
        0.4423002004623413
      ]
    },
    {
      "coordinates": [
        113,
        170
      ],
      "magnitude": 1.6038004159927368,
      "direction": [
        0.39944300055503845,
        0.9167580008506775
      ]
    },
    {
      "coordinates": [
        136,
        170
      ],
      "magnitude": 3.2517495155334473,
      "direction": [
        0.8194419145584106,
        0.5731621384620667
      ]
    },
    {
      "coordinates": [
        159,
        170
      ],
      "magnitude": 3.8801257610321045,
      "direction": [
        0.8435094952583313,
        0.5371142029762268
      ]
    },
    {
      "coordinates": [
        182,
        170
      ],
      "magnitude": 5.327554225921631,
      "direction": [
        0.8920636773109436,
        0.45190978050231934
      ]
    },
    {
      "coordinates": [
        205,
        170
      ],
      "magnitude": 5.510791778564453,
      "direction": [
        0.941236138343811,
        0.33774927258491516
      ]
    },
    {
      "coordinates": [
        227,
        170
      ],
      "magnitude": 5.889699935913086,
      "direction": [
        0.9960859417915344,
        0.08839021623134613
      ]
    },
    {
      "coordinates": [
        250,
        170
      ],
      "magnitude": 6.895733833312988,
      "direction": [
        0.9998926520347595,
        0.014651048928499222
      ]
    },
    {
      "coordinates": [
        273,
        170
      ],
      "magnitude": 6.750603199005127,
      "direction": [
        0.9994304776191711,
        -0.03374429792165756
      ]
    },
    {
      "coordinates": [
        296,
        170
      ],
      "magnitude": 6.242773056030273,
      "direction": [
        0.9985143542289734,
        -0.05448838695883751
      ]
    },
    {
      "coordinates": [
        319,
        170
      ],
      "magnitude": 5.5968451499938965,
      "direction": [
        0.9999168515205383,
        -0.012897075153887272
      ]
    },
    {
      "coordinates": [
        0,
        187
      ],
      "magnitude": 6.702780246734619,
      "direction": [
        -0.9530887007713318,
        0.3026909828186035
      ]
    },
    {
      "coordinates": [
        22,
        187
      ],
      "magnitude": 6.447853088378906,
      "direction": [
        -0.9454425573348999,
        0.3257889151573181
      ]
    },
    {
      "coordinates": [
        45,
        187
      ],
      "magnitude": 5.896397590637207,
      "direction": [
        -0.9277063012123108,
        0.37331098318099976
      ]
    },
    {
      "coordinates": [
        68,
        187
      ],
      "magnitude": 4.3499603271484375,
      "direction": [
        -0.7682704925537109,
        0.6401252746582031
      ]
    },
    {
      "coordinates": [
        91,
        187
      ],
      "magnitude": 2.5878548622131348,
      "direction": [
        -0.4657295048236847,
        0.8849272131919861
      ]
    },
    {
      "coordinates": [
        113,
        187
      ],
      "magnitude": 3.0685207843780518,
      "direction": [
        0.13068324327468872,
        0.9914241433143616
      ]
    },
    {
      "coordinates": [
        136,
        187
      ],
      "magnitude": 4.17125129699707,
      "direction": [
        0.5001147985458374,
        0.865959107875824
      ]
    },
    {
      "coordinates": [
        159,
        187
      ],
      "magnitude": 5.4513163566589355,
      "direction": [
        0.6366605162620544,
        0.7711442112922668
      ]
    },
    {
      "coordinates": [
        182,
        187
      ],
      "magnitude": 6.914933681488037,
      "direction": [
        0.7518888115882874,
        0.6592899560928345
      ]
    },
    {
      "coordinates": [
        205,
        187
      ],
      "magnitude": 6.419188499450684,
      "direction": [
        0.8521225452423096,
        0.5233422517776489
      ]
    },
    {
      "coordinates": [
        227,
        187
      ],
      "magnitude": 6.468541145324707,
      "direction": [
        0.9406421780586243,
        0.33939990401268005
      ]
    },
    {
      "coordinates": [
        250,
        187
      ],
      "magnitude": 7.302828788757324,
      "direction": [
        0.9895731806755066,
        0.14403091371059418
      ]
    },
    {
      "coordinates": [
        273,
        187
      ],
      "magnitude": 6.7661824226379395,
      "direction": [
        0.9914872050285339,
        0.13020426034927368
      ]
    },
    {
      "coordinates": [
        296,
        187
      ],
      "magnitude": 6.752682209014893,
      "direction": [
        0.9938177466392517,
        0.11102372407913208
      ]
    },
    {
      "coordinates": [
        319,
        187
      ],
      "magnitude": 5.882817268371582,
      "direction": [
        0.9997497200965881,
        0.022370342165231705
      ]
    },
    {
      "coordinates": [
        0,
        204
      ],
      "magnitude": 7.049973011016846,
      "direction": [
        -0.9351633787155151,
        0.35421672463417053
      ]
    },
    {
      "coordinates": [
        22,
        204
      ],
      "magnitude": 7.563732147216797,
      "direction": [
        -0.8761313557624817,
        0.4820724427700043
      ]
    },
    {
      "coordinates": [
        45,
        204
      ],
      "magnitude": 7.226077556610107,
      "direction": [
        -0.8199171423912048,
        0.5724822878837585
      ]
    },
    {
      "coordinates": [
        68,
        204
      ],
      "magnitude": 5.406565189361572,
      "direction": [
        -0.6812047362327576,
        0.732093095779419
      ]
    },
    {
      "coordinates": [
        91,
        204
      ],
      "magnitude": 4.396799564361572,
      "direction": [
        -0.35588106513023376,
        0.9345312118530273
      ]
    },
    {
      "coordinates": [
        113,
        204
      ],
      "magnitude": 5.154602527618408,
      "direction": [
        -0.0662330612540245,
        0.9978041648864746
      ]
    },
    {
      "coordinates": [
        136,
        204
      ],
      "magnitude": 5.350338459014893,
      "direction": [
        0.35756486654281616,
        0.9338882565498352
      ]
    },
    {
      "coordinates": [
        159,
        204
      ],
      "magnitude": 6.658077239990234,
      "direction": [
        0.4943653345108032,
        0.8692541718482971
      ]
    },
    {
      "coordinates": [
        182,
        204
      ],
      "magnitude": 8.377229690551758,
      "direction": [
        0.5740614533424377,
        0.8188121914863586
      ]
    },
    {
      "coordinates": [
        205,
        204
      ],
      "magnitude": 7.611405372619629,
      "direction": [
        0.8002042770385742,
        0.5997275114059448
      ]
    },
    {
      "coordinates": [
        227,
        204
      ],
      "magnitude": 7.516692161560059,
      "direction": [
        0.8562560677528381,
        0.5165515542030334
      ]
    },
    {
      "coordinates": [
        250,
        204
      ],
      "magnitude": 7.5417609214782715,
      "direction": [
        0.931724488735199,
        0.3631657361984253
      ]
    },
    {
      "coordinates": [
        273,
        204
      ],
      "magnitude": 7.229336261749268,
      "direction": [
        0.96805739402771,
        0.2507284879684448
      ]
    },
    {
      "coordinates": [
        296,
        204
      ],
      "magnitude": 7.059045314788818,
      "direction": [
        0.9874369502067566,
        0.15801368653774261
      ]
    },
    {
      "coordinates": [
        319,
        204
      ],
      "magnitude": 6.0011420249938965,
      "direction": [
        0.998556911945343,
        0.053705062717199326
      ]
    },
    {
      "coordinates": [
        0,
        221
      ],
      "magnitude": 7.729427814483643,
      "direction": [
        -0.8692900538444519,
        0.49430233240127563
      ]
    },
    {
      "coordinates": [
        22,
        221
      ],
      "magnitude": 8.091056823730469,
      "direction": [
        -0.8104960918426514,
        0.5857440829277039
      ]
    },
    {
      "coordinates": [
        45,
        221
      ],
      "magnitude": 7.602503299713135,
      "direction": [
        -0.6704176664352417,
        0.741983950138092
      ]
    },
    {
      "coordinates": [
        68,
        221
      ],
      "magnitude": 7.088170051574707,
      "direction": [
        -0.5310001969337463,
        0.8473716974258423
      ]
    },
    {
      "coordinates": [
        91,
        221
      ],
      "magnitude": 6.506023406982422,
      "direction": [
        -0.25791823863983154,
        0.9661667346954346
      ]
    },
    {
      "coordinates": [
        113,
        221
      ],
      "magnitude": 6.689948558807373,
      "direction": [
        -0.06155295670032501,
        0.9981037974357605
      ]
    },
    {
      "coordinates": [
        136,
        221
      ],
      "magnitude": 7.318037986755371,
      "direction": [
        0.258127897977829,
        0.9661107063293457
      ]
    },
    {
      "coordinates": [
        159,
        221
      ],
      "magnitude": 8.313082695007324,
      "direction": [
        0.4012030363082886,
        0.9159891605377197
      ]
    },
    {
      "coordinates": [
        182,
        221
      ],
      "magnitude": 9.237788200378418,
      "direction": [
        0.4892062842845917,
        0.8721680641174316
      ]
    },
    {
      "coordinates": [
        205,
        221
      ],
      "magnitude": 8.922308921813965,
      "direction": [
        0.7122008204460144,
        0.7019757628440857
      ]
    },
    {
      "coordinates": [
        227,
        221
      ],
      "magnitude": 8.402361869812012,
      "direction": [
        0.8174071311950684,
        0.5760602951049805
      ]
    },
    {
      "coordinates": [
        250,
        221
      ],
      "magnitude": 8.17615795135498,
      "direction": [
        0.8570763468742371,
        0.5151894092559814
      ]
    },
    {
      "coordinates": [
        273,
        221
      ],
      "magnitude": 8.144325256347656,
      "direction": [
        0.9222639799118042,
        0.3865607976913452
      ]
    },
    {
      "coordinates": [
        296,
        221
      ],
      "magnitude": 6.912036418914795,
      "direction": [
        0.9629342555999756,
        0.2697363495826721
      ]
    },
    {
      "coordinates": [
        319,
        221
      ],
      "magnitude": 5.8715996742248535,
      "direction": [
        0.9875118136405945,
        0.15754514932632446
      ]
    },
    {
      "coordinates": [
        0,
        239
      ],
      "magnitude": 7.775941848754883,
      "direction": [
        -0.7836742401123047,
        0.6211720705032349
      ]
    },
    {
      "coordinates": [
        22,
        239
      ],
      "magnitude": 8.699844360351562,
      "direction": [
        -0.7065273523330688,
        0.707685649394989
      ]
    },
    {
      "coordinates": [
        45,
        239
      ],
      "magnitude": 8.434670448303223,
      "direction": [
        -0.5614148378372192,
        0.8275344967842102
      ]
    },
    {
      "coordinates": [
        68,
        239
      ],
      "magnitude": 8.278748512268066,
      "direction": [
        -0.42341291904449463,
        0.9059367775917053
      ]
    },
    {
      "coordinates": [
        91,
        239
      ],
      "magnitude": 7.795496940612793,
      "direction": [
        -0.22966288030147552,
        0.9732702374458313
      ]
    },
    {
      "coordinates": [
        113,
        239
      ],
      "magnitude": 7.724214553833008,
      "direction": [
        -0.00840291939675808,
        0.9999647736549377
      ]
    },
    {
      "coordinates": [
        136,
        239
      ],
      "magnitude": 9.537094116210938,
      "direction": [
        0.25548574328422546,
        0.9668128490447998
      ]
    },
    {
      "coordinates": [
        159,
        239
      ],
      "magnitude": 10.87381649017334,
      "direction": [
        0.2924000322818756,
        0.9562960863113403
      ]
    },
    {
      "coordinates": [
        182,
        239
      ],
      "magnitude": 10.906354904174805,
      "direction": [
        0.42735862731933594,
        0.904082179069519
      ]
    },
    {
      "coordinates": [
        205,
        239
      ],
      "magnitude": 10.181005477905273,
      "direction": [
        0.6205759048461914,
        0.7841464281082153
      ]
    },
    {
      "coordinates": [
        227,
        239
      ],
      "magnitude": 9.432456970214844,
      "direction": [
        0.7250359654426575,
        0.6887109279632568
      ]
    },
    {
      "coordinates": [
        250,
        239
      ],
      "magnitude": 8.671990394592285,
      "direction": [
        0.8136703372001648,
        0.5813266038894653
      ]
    },
    {
      "coordinates": [
        273,
        239
      ],
      "magnitude": 8.11458969116211,
      "direction": [
        0.8886759877204895,
        0.4585358202457428
      ]
    },
    {
      "coordinates": [
        296,
        239
      ],
      "magnitude": 7.022543907165527,
      "direction": [
        0.9221798181533813,
        0.38676124811172485
      ]
    },
    {
      "coordinates": [
        319,
        239
      ],
      "magnitude": 5.717887878417969,
      "direction": [
        0.9728620052337646,
        0.23138581216335297
      ]
    }
  ],
  "shear_mesh": [
    {
      "coordinates": [
        0,
        0
      ],
      "magnitude": 2.2781198024749756,
      "direction": [
        0.9249391555786133,
        0.38011518120765686
      ]
    },
    {
      "coordinates": [
        22,
        0
      ],
      "magnitude": 2.4470505714416504,
      "direction": [
        0.8741933703422546,
        0.48557788133621216
      ]
    },
    {
      "coordinates": [
        45,
        0
      ],
      "magnitude": 2.3694090843200684,
      "direction": [
        0.806117832660675,
        0.5917549729347229
      ]
    },
    {
      "coordinates": [
        68,
        0
      ],
      "magnitude": 2.137077808380127,
      "direction": [
        0.8033841252326965,
        0.5954610705375671
      ]
    },
    {
      "coordinates": [
        91,
        0
      ],
      "magnitude": 2.2239322662353516,
      "direction": [
        0.6992157101631165,
        0.7149107456207275
      ]
    },
    {
      "coordinates": [
        113,
        0
      ],
      "magnitude": 2.481001853942871,
      "direction": [
        0.7242904901504517,
        0.6894950270652771
      ]
    },
    {
      "coordinates": [
        136,
        0
      ],
      "magnitude": 2.2089426517486572,
      "direction": [
        0.6154693961143494,
        0.7881607413291931
      ]
    },
    {
      "coordinates": [
        159,
        0
      ],
      "magnitude": 1.9612834453582764,
      "direction": [
        0.47594544291496277,
        0.8794748187065125
      ]
    },
    {
      "coordinates": [
        182,
        0
      ],
      "magnitude": 2.408841848373413,
      "direction": [
        0.3207593560218811,
        0.9471607208251953
      ]
    },
    {
      "coordinates": [
        205,
        0
      ],
      "magnitude": 1.8082342147827148,
      "direction": [
        0.2718971371650696,
        0.9623262882232666
      ]
    },
    {
      "coordinates": [
        227,
        0
      ],
      "magnitude": 1.3683165311813354,
      "direction": [
        0.18902833759784698,
        0.9819715619087219
      ]
    },
    {
      "coordinates": [
        250,
        0
      ],
      "magnitude": 1.4974478483200073,
      "direction": [
        0.2785930633544922,
        0.9604092836380005
      ]
    },
    {
      "coordinates": [
        273,
        0
      ],
      "magnitude": 1.194936752319336,
      "direction": [
        0.34114062786102295,
        0.9400123357772827
      ]
    },
    {
      "coordinates": [
        296,
        0
      ],
      "magnitude": 1.1212987899780273,
      "direction": [
        0.44858914613723755,
        0.8937380909919739
      ]
    },
    {
      "coordinates": [
        319,
        0
      ],
      "magnitude": 1.024338960647583,
      "direction": [
        0.5580739378929138,
        0.829791247844696
      ]
    },
    {
      "coordinates": [
        0,
        17
      ],
      "magnitude": 2.153247356414795,
      "direction": [
        0.9245580434799194,
        0.38104137778282166
      ]
    },
    {
      "coordinates": [
        22,
        17
      ],
      "magnitude": 2.5545568466186523,
      "direction": [
        0.8544256687164307,
        0.5195736289024353
      ]
    },
    {
      "coordinates": [
        45,
        17
      ],
      "magnitude": 2.5233964920043945,
      "direction": [
        0.8027349710464478,
        0.5963360071182251
      ]
    },
    {
      "coordinates": [
        68,
        17
      ],
      "magnitude": 2.335280656814575,
      "direction": [
        0.7729538083076477,
        0.634462296962738
      ]
    },
    {
      "coordinates": [
        91,
        17
      ],
      "magnitude": 2.314824342727661,
      "direction": [
        0.7527501583099365,
        0.658306360244751
      ]
    },
    {
      "coordinates": [
        113,
        17
      ],
      "magnitude": 2.44793963432312,
      "direction": [
        0.5914525985717773,
        0.8063398599624634
      ]
    },
    {
      "coordinates": [
        136,
        17
      ],
      "magnitude": 2.230816602706909,
      "direction": [
        0.43979379534721375,
        0.8980987071990967
      ]
    },
    {
      "coordinates": [
        159,
        17
      ],
      "magnitude": 2.1269025802612305,
      "direction": [
        0.3400278687477112,
        0.9404153823852539
      ]
    },
    {
      "coordinates": [
        182,
        17
      ],
      "magnitude": 2.4438631534576416,
      "direction": [
        0.23609870672225952,
        0.971729040145874
      ]
    },
    {
      "coordinates": [
        205,
        17
      ],
      "magnitude": 1.9318684339523315,
      "direction": [
        0.27113616466522217,
        0.9625409841537476
      ]
    },
    {
      "coordinates": [
        227,
        17
      ],
      "magnitude": 1.4718395471572876,
      "direction": [
        0.2757863402366638,
        0.9612190127372742
      ]
    },
    {
      "coordinates": [
        250,
        17
      ],
      "magnitude": 1.4145159721374512,
      "direction": [
        0.17293617129325867,
        0.9849330186843872
      ]
    },
    {
      "coordinates": [
        273,
        17
      ],
      "magnitude": 1.1564828157424927,
      "direction": [
        0.2399548888206482,
        0.970784068107605
      ]
    },
    {
      "coordinates": [
        296,
        17
      ],
      "magnitude": 0.9164109826087952,
      "direction": [
        0.4011000990867615,
        0.9160342216491699
      ]
    },
    {
      "coordinates": [
        319,
        17
      ],
      "magnitude": 1.0616273880004883,
      "direction": [
        0.6014878153800964,
        0.7988819479942322
      ]
    },
    {
      "coordinates": [
        0,
        34
      ],
      "magnitude": 2.1638243198394775,
      "direction": [
        0.942112147808075,
        0.33529800176620483
      ]
    },
    {
      "coordinates": [
        22,
        34
      ],
      "magnitude": 2.2654824256896973,
      "direction": [
        0.8541365265846252,
        0.5200487971305847
      ]
    },
    {
      "coordinates": [
        45,
        34
      ],
      "magnitude": 2.8362221717834473,
      "direction": [
        0.8403927087783813,
        0.5419779419898987
      ]
    },
    {
      "coordinates": [
        68,
        34
      ],
      "magnitude": 2.7881877422332764,
      "direction": [
        0.7859074473381042,
        0.6183441281318665
      ]
    },
    {
      "coordinates": [
        91,
        34
      ],
      "magnitude": 2.57796049118042,
      "direction": [
        0.7541263699531555,
        0.6567293405532837
      ]
    },
    {
      "coordinates": [
        113,
        34
      ],
      "magnitude": 2.7593483924865723,
      "direction": [
        0.600184440612793,
        0.7998616695404053
      ]
    },
    {
      "coordinates": [
        136,
        34
      ],
      "magnitude": 2.6550488471984863,
      "direction": [
        0.5122686624526978,
        0.8588253259658813
      ]
    },
    {
      "coordinates": [
        159,
        34
      ],
      "magnitude": 2.5006802082061768,
      "direction": [
        0.3769627511501312,
        0.926228404045105
      ]
    },
    {
      "coordinates": [
        182,
        34
      ],
      "magnitude": 2.486194372177124,
      "direction": [
        0.21283993124961853,
        0.9770870208740234
      ]
    },
    {
      "coordinates": [
        205,
        34
      ],
      "magnitude": 1.9466668367385864,
      "direction": [
        0.22667983174324036,
        0.9739693403244019
      ]
    },
    {
      "coordinates": [
        227,
        34
      ],
      "magnitude": 1.672727108001709,
      "direction": [
        0.18813282251358032,
        0.9821436405181885
      ]
    },
    {
      "coordinates": [
        250,
        34
      ],
      "magnitude": 1.4490196704864502,
      "direction": [
        0.03737349808216095,
        0.9993013739585876
      ]
    },
    {
      "coordinates": [
        273,
        34
      ],
      "magnitude": 1.0580099821090698,
      "direction": [
        0.1158752366900444,
        0.993263840675354
      ]
    },
    {
      "coordinates": [
        296,
        34
      ],
      "magnitude": 0.7705965638160706,
      "direction": [
        0.44123873114585876,
        0.8973897695541382
      ]
    },
    {
      "coordinates": [
        319,
        34
      ],
      "magnitude": 0.8462527394294739,
      "direction": [
        0.41670259833335876,
        0.9090429544448853
      ]
    },
    {
      "coordinates": [
        0,
        51
      ],
      "magnitude": 2.647829294204712,
      "direction": [
        0.9016931653022766,
        0.4323763847351074
      ]
    },
    {
      "coordinates": [
        22,
        51
      ],
      "magnitude": 2.502497911453247,
      "direction": [
        0.9047294855117798,
        0.42598655819892883
      ]
    },
    {
      "coordinates": [
        45,
        51
      ],
      "magnitude": 2.633760929107666,
      "direction": [
        0.7914729714393616,
        0.6112040877342224
      ]
    },
    {
      "coordinates": [
        68,
        51
      ],
      "magnitude": 2.8487868309020996,
      "direction": [
        0.7147601842880249,
        0.6993696093559265
      ]
    },
    {
      "coordinates": [
        91,
        51
      ],
      "magnitude": 2.4910712242126465,
      "direction": [
        0.6414113640785217,
        0.7671971917152405
      ]
    },
    {
      "coordinates": [
        113,
        51
      ],
      "magnitude": 2.7212295532226562,
      "direction": [
        0.5613867044448853,
        0.8275536298751831
      ]
    },
    {
      "coordinates": [
        136,
        51
      ],
      "magnitude": 3.0414109230041504,
      "direction": [
        0.527708888053894,
        0.8494252562522888
      ]
    },
    {
      "coordinates": [
        159,
        51
      ],
      "magnitude": 2.8044488430023193,
      "direction": [
        0.3979682922363281,
        0.9173991680145264
      ]
    },
    {
      "coordinates": [
        182,
        51
      ],
      "magnitude": 2.84804368019104,
      "direction": [
        0.24811182916164398,
        0.9687314033508301
      ]
    },
    {
      "coordinates": [
        205,
        51
      ],
      "magnitude": 2.1245529651641846,
      "direction": [
        0.12735429406166077,
        0.9918572902679443
      ]
    },
    {
      "coordinates": [
        227,
        51
      ],
      "magnitude": 1.727810263633728,
      "direction": [
        0.0024343389086425304,
        0.9999970197677612
      ]
    },
    {
      "coordinates": [
        250,
        51
      ],
      "magnitude": 1.432797908782959,
      "direction": [
        0.13364805281162262,
        0.9910288453102112
      ]
    },
    {
      "coordinates": [
        273,
        51
      ],
      "magnitude": 1.0485711097717285,
      "direction": [
        0.3549215793609619,
        0.9348959922790527
      ]
    },
    {
      "coordinates": [
        296,
        51
      ],
      "magnitude": 0.6809546947479248,
      "direction": [
        0.35705262422561646,
        0.9340842366218567
      ]
    },
    {
      "coordinates": [
        319,
        51
      ],
      "magnitude": 0.847856342792511,
      "direction": [
        0.59568852186203,
        0.803215503692627
      ]
    },
    {
      "coordinates": [
        0,
        68
      ],
      "magnitude": 2.228811264038086,
      "direction": [
        0.8706538677215576,
        0.4918961226940155
      ]
    },
    {
      "coordinates": [
        22,
        68
      ],
      "magnitude": 2.43617582321167,
      "direction": [
        0.8345791697502136,
        0.5508880019187927
      ]
    },
    {
      "coordinates": [
        45,
        68
      ],
      "magnitude": 2.5560872554779053,
      "direction": [
        0.7093950510025024,
        0.7048110961914062
      ]
    },
    {
      "coordinates": [
        68,
        68
      ],
      "magnitude": 2.492671251296997,
      "direction": [
        0.6246536374092102,
        0.7809019088745117
      ]
    },
    {
      "coordinates": [
        91,
        68
      ],
      "magnitude": 2.6743454933166504,
      "direction": [
        0.551474928855896,
        0.8341915011405945
      ]
    },
    {
      "coordinates": [
        113,
        68
      ],
      "magnitude": 2.585463762283325,
      "direction": [
        0.5178147554397583,
        0.8554928302764893
      ]
    },
    {
      "coordinates": [
        136,
        68
      ],
      "magnitude": 2.7833902835845947,
      "direction": [
        0.39672547578811646,
        0.9179373383522034
      ]
    },
    {
      "coordinates": [
        159,
        68
      ],
      "magnitude": 3.050597667694092,
      "direction": [
        0.34069639444351196,
        0.940173327922821
      ]
    },
    {
      "coordinates": [
        182,
        68
      ],
      "magnitude": 3.05891489982605,
      "direction": [
        0.22116626799106598,
        0.9752361178398132
      ]
    },
    {
      "coordinates": [
        205,
        68
      ],
      "magnitude": 2.4754903316497803,
      "direction": [
        0.14183007180690765,
        0.9898910522460938
      ]
    },
    {
      "coordinates": [
        227,
        68
      ],
      "magnitude": 1.6455239057540894,
      "direction": [
        0.0886690616607666,
        0.9960610866546631
      ]
    },
    {
      "coordinates": [
        250,
        68
      ],
      "magnitude": 1.308482050895691,
      "direction": [
        0.19638276100158691,
        0.9805272817611694
      ]
    },
    {
      "coordinates": [
        273,
        68
      ],
      "magnitude": 1.0694242715835571,
      "direction": [
        0.33329716324806213,
        0.942821741104126
      ]
    },
    {
      "coordinates": [
        296,
        68
      ],
      "magnitude": 0.6133190989494324,
      "direction": [
        0.24894079566001892,
        0.9685186743736267
      ]
    },
    {
      "coordinates": [
        319,
        68
      ],
      "magnitude": 0.5670888423919678,
      "direction": [
        0.7843003273010254,
        0.6203812956809998
      ]
    },
    {
      "coordinates": [
        0,
        85
      ],
      "magnitude": 2.1235649585723877,
      "direction": [
        0.8369356393814087,
        0.5473012328147888
      ]
    },
    {
      "coordinates": [
        22,
        85
      ],
      "magnitude": 2.0833187103271484,
      "direction": [
        0.8148751854896545,
        0.5796363949775696
      ]
    },
    {
      "coordinates": [
        45,
        85
      ],
      "magnitude": 2.3231093883514404,
      "direction": [
        0.6763339042663574,
        0.7365951538085938
      ]
    },
    {
      "coordinates": [
        68,
        85
      ],
      "magnitude": 2.574070930480957,
      "direction": [
        0.5493201017379761,
        0.8356119394302368
      ]
    },
    {
      "coordinates": [
        91,
        85
      ],
      "magnitude": 2.510221481323242,
      "direction": [
        0.5249485969543457,
        0.8511339426040649
      ]
    },
    {
      "coordinates": [
        113,
        85
      ],
      "magnitude": 2.6821448802948,
      "direction": [
        0.41953662037849426,
        0.9077383875846863
      ]
    },
    {
      "coordinates": [
        136,
        85
      ],
      "magnitude": 2.820297956466675,
      "direction": [
        0.3401985764503479,
        0.9403536319732666
      ]
    },
    {
      "coordinates": [
        159,
        85
      ],
      "magnitude": 3.154731512069702,
      "direction": [
        0.3052084743976593,
        0.9522855281829834
      ]
    },
    {
      "coordinates": [
        182,
        85
      ],
      "magnitude": 3.376410961151123,
      "direction": [
        0.17947688698768616,
        0.9837622046470642
      ]
    },
    {
      "coordinates": [
        205,
        85
      ],
      "magnitude": 2.5503573417663574,
      "direction": [
        0.09529036283493042,
        0.9954495429992676
      ]
    },
    {
      "coordinates": [
        227,
        85
      ],
      "magnitude": 1.7301509380340576,
      "direction": [
        0.1014103814959526,
        0.9948446750640869
      ]
    },
    {
      "coordinates": [
        250,
        85
      ],
      "magnitude": 1.2294156551361084,
      "direction": [
        0.37623655796051025,
        0.9265236258506775
      ]
    },
    {
      "coordinates": [
        273,
        85
      ],
      "magnitude": 1.242590069770813,
      "direction": [
        0.2801581025123596,
        0.9599538445472717
      ]
    },
    {
      "coordinates": [
        296,
        85
      ],
      "magnitude": 0.7265381217002869,
      "direction": [
        0.7814815640449524,
        0.6239283680915833
      ]
    },
    {
      "coordinates": [
        319,
        85
      ],
      "magnitude": 0.6825354099273682,
      "direction": [
        0.9892287254333496,
        0.14637823402881622
      ]
    },
    {
      "coordinates": [
        0,
        102
      ],
      "magnitude": 1.8761533498764038,
      "direction": [
        0.6937423348426819,
        0.7202233076095581
      ]
    },
    {
      "coordinates": [
        22,
        102
      ],
      "magnitude": 1.6550543308258057,
      "direction": [
        0.7093271613121033,
        0.7048794627189636
      ]
    },
    {
      "coordinates": [
        45,
        102
      ],
      "magnitude": 2.0655429363250732,
      "direction": [
        0.5235204100608826,
        0.8520131707191467
      ]
    },
    {
      "coordinates": [
        68,
        102
      ],
      "magnitude": 2.4529662132263184,
      "direction": [
        0.4244324564933777,
        0.9054596424102783
      ]
    },
    {
      "coordinates": [
        91,
        102
      ],
      "magnitude": 2.5276987552642822,
      "direction": [
        0.482164591550827,
        0.8760806918144226
      ]
    },
    {
      "coordinates": [
        113,
        102
      ],
      "magnitude": 2.833812952041626,
      "direction": [
        0.4114478528499603,
        0.9114332795143127
      ]
    },
    {
      "coordinates": [
        136,
        102
      ],
      "magnitude": 2.8896124362945557,
      "direction": [
        0.34599339962005615,
        0.9382369518280029
      ]
    },
    {
      "coordinates": [
        159,
        102
      ],
      "magnitude": 3.2708990573883057,
      "direction": [
        0.2494213581085205,
        0.9683950543403625
      ]
    },
    {
      "coordinates": [
        182,
        102
      ],
      "magnitude": 3.5730183124542236,
      "direction": [
        0.20102041959762573,
        0.9795870780944824
      ]
    },
    {
      "coordinates": [
        205,
        102
      ],
      "magnitude": 2.7295563220977783,
      "direction": [
        0.1318463832139969,
        0.9912701845169067
      ]
    },
    {
      "coordinates": [
        227,
        102
      ],
      "magnitude": 1.6998478174209595,
      "direction": [
        0.16648994386196136,
        0.9860431551933289
      ]
    },
    {
      "coordinates": [
        250,
        102
      ],
      "magnitude": 1.0891762971878052,
      "direction": [
        0.14911587536334991,
        0.9888196587562561
      ]
    },
    {
      "coordinates": [
        273,
        102
      ],
      "magnitude": 1.0567004680633545,
      "direction": [
        0.48036912083625793,
        0.8770663738250732
      ]
    },
    {
      "coordinates": [
        296,
        102
      ],
      "magnitude": 0.8378798961639404,
      "direction": [
        0.8540710210800171,
        0.5201563239097595
      ]
    },
    {
      "coordinates": [
        319,
        102
      ],
      "magnitude": 0.7985914945602417,
      "direction": [
        0.9696949124336243,
        0.24431923031806946
      ]
    },
    {
      "coordinates": [
        0,
        119
      ],
      "magnitude": 1.631929874420166,
      "direction": [
        0.7808477282524109,
        0.6247214078903198
      ]
    },
    {
      "coordinates": [
        22,
        119
      ],
      "magnitude": 2.1026899814605713,
      "direction": [
        0.6687052249908447,
        0.7435276508331299
      ]
    },
    {
      "coordinates": [
        45,
        119
      ],
      "magnitude": 2.0179388523101807,
      "direction": [
        0.4485440254211426,
        0.8937607407569885
      ]
    },
    {
      "coordinates": [
        68,
        119
      ],
      "magnitude": 2.2054250240325928,
      "direction": [
        0.42339953780174255,
        0.9059430360794067
      ]
    },
    {
      "coordinates": [
        91,
        119
      ],
      "magnitude": 2.383179187774658,
      "direction": [
        0.33780691027641296,
        0.9412153959274292
      ]
    },
    {
      "coordinates": [
        113,
        119
      ],
      "magnitude": 2.697089910507202,
      "direction": [
        0.3612079620361328,
        0.9324852228164673
      ]
    },
    {
      "coordinates": [
        136,
        119
      ],
      "magnitude": 2.9595415592193604,
      "direction": [
        0.3054955005645752,
        0.952193558216095
      ]
    },
    {
      "coordinates": [
        159,
        119
      ],
      "magnitude": 3.44704532623291,
      "direction": [
        0.2553197145462036,
        0.9668567180633545
      ]
    },
    {
      "coordinates": [
        182,
        119
      ],
      "magnitude": 3.7530694007873535,
      "direction": [
        0.17701329290866852,
        0.9842084646224976
      ]
    },
    {
      "coordinates": [
        205,
        119
      ],
      "magnitude": 2.911125898361206,
      "direction": [
        0.1918097883462906,
        0.9814320802688599
      ]
    },
    {
      "coordinates": [
        227,
        119
      ],
      "magnitude": 1.7925952672958374,
      "direction": [
        0.26537248492240906,
        0.9641459584236145
      ]
    },
    {
      "coordinates": [
        250,
        119
      ],
      "magnitude": 1.13383948802948,
      "direction": [
        0.40795210003852844,
        0.9130033850669861
      ]
    },
    {
      "coordinates": [
        273,
        119
      ],
      "magnitude": 0.810310959815979,
      "direction": [
        0.4505418837070465,
        0.8927552103996277
      ]
    },
    {
      "coordinates": [
        296,
        119
      ],
      "magnitude": 0.8949754238128662,
      "direction": [
        0.9069789052009583,
        0.4211761951446533
      ]
    },
    {
      "coordinates": [
        319,
        119
      ],
      "magnitude": 0.7206751108169556,
      "direction": [
        0.9334399700164795,
        0.3587336540222168
      ]
    },
    {
      "coordinates": [
        0,
        136
      ],
      "magnitude": 1.3362938165664673,
      "direction": [
        0.7290045619010925,
        0.6845088601112366
      ]
    },
    {
      "coordinates": [
        22,
        136
      ],
      "magnitude": 1.8416529893875122,
      "direction": [
        0.4921536147594452,
        0.8705083727836609
      ]
    },
    {
      "coordinates": [
        45,
        136
      ],
      "magnitude": 2.2669172286987305,
      "direction": [
        0.46964043378829956,
        0.8828578591346741
      ]
    },
    {
      "coordinates": [
        68,
        136
      ],
      "magnitude": 2.3311033248901367,
      "direction": [
        0.31308168172836304,
        0.9497261643409729
      ]
    },
    {
      "coordinates": [
        91,
        136
      ],
      "magnitude": 2.3823368549346924,
      "direction": [
        0.4152565896511078,
        0.9097042679786682
      ]
    },
    {
      "coordinates": [
        113,
        136
      ],
      "magnitude": 2.6917924880981445,
      "direction": [
        0.3745894134044647,
        0.9271908402442932
      ]
    },
    {
      "coordinates": [
        136,
        136
      ],
      "magnitude": 3.020993947982788,
      "direction": [
        0.34260162711143494,
        0.9394807815551758
      ]
    },
    {
      "coordinates": [
        159,
        136
      ],
      "magnitude": 3.6546897888183594,
      "direction": [
        0.28060534596443176,
        0.9598232507705688
      ]
    },
    {
      "coordinates": [
        182,
        136
      ],
      "magnitude": 3.816404104232788,
      "direction": [
        0.1693315953016281,
        0.9855591058731079
      ]
    },
    {
      "coordinates": [
        205,
        136
      ],
      "magnitude": 2.901179552078247,
      "direction": [
        0.16717231273651123,
        0.9859277606010437
      ]
    },
    {
      "coordinates": [
        227,
        136
      ],
      "magnitude": 1.9513696432113647,
      "direction": [
        0.2851903736591339,
        0.9584709405899048
      ]
    },
    {
      "coordinates": [
        250,
        136
      ],
      "magnitude": 1.147566556930542,
      "direction": [
        0.3786082863807678,
        0.9255570769309998
      ]
    },
    {
      "coordinates": [
        273,
        136
      ],
      "magnitude": 0.9030227661132812,
      "direction": [
        0.8258466124534607,
        0.5638948082923889
      ]
    },
    {
      "coordinates": [
        296,
        136
      ],
      "magnitude": 0.7489891648292542,
      "direction": [
        0.9624434113502502,
        0.2714821696281433
      ]
    },
    {
      "coordinates": [
        319,
        136
      ],
      "magnitude": 0.9825606346130371,
      "direction": [
        0.951934814453125,
        0.3063005805015564
      ]
    },
    {
      "coordinates": [
        0,
        153
      ],
      "magnitude": 1.554506778717041,
      "direction": [
        0.5550647377967834,
        0.8318071961402893
      ]
    },
    {
      "coordinates": [
        22,
        153
      ],
      "magnitude": 1.686694622039795,
      "direction": [
        0.4080261290073395,
        0.912970244884491
      ]
    },
    {
      "coordinates": [
        45,
        153
      ],
      "magnitude": 2.197664976119995,
      "direction": [
        0.30528441071510315,
        0.9522611498832703
      ]
    },
    {
      "coordinates": [
        68,
        153
      ],
      "magnitude": 2.2024879455566406,
      "direction": [
        0.38584670424461365,
        0.9225629568099976
      ]
    },
    {
      "coordinates": [
        91,
        153
      ],
      "magnitude": 2.0754711627960205,
      "direction": [
        0.3453153073787689,
        0.9384866952896118
      ]
    },
    {
      "coordinates": [
        113,
        153
      ],
      "magnitude": 2.6362104415893555,
      "direction": [
        0.36550408601760864,
        0.9308097958564758
      ]
    },
    {
      "coordinates": [
        136,
        153
      ],
      "magnitude": 2.9588613510131836,
      "direction": [
        0.34752368927001953,
        0.9376711845397949
      ]
    },
    {
      "coordinates": [
        159,
        153
      ],
      "magnitude": 3.73417329788208,
      "direction": [
        0.224213108420372,
        0.974540114402771
      ]
    },
    {
      "coordinates": [
        182,
        153
      ],
      "magnitude": 4.002775192260742,
      "direction": [
        0.22187234461307526,
        0.9750757217407227
      ]
    },
    {
      "coordinates": [
        205,
        153
      ],
      "magnitude": 3.0782132148742676,
      "direction": [
        0.28195035457611084,
        0.9594289660453796
      ]
    },
    {
      "coordinates": [
        227,
        153
      ],
      "magnitude": 1.817467451095581,
      "direction": [
        0.2874458432197571,
        0.9577968716621399
      ]
    },
    {
      "coordinates": [
        250,
        153
      ],
      "magnitude": 1.310580849647522,
      "direction": [
        0.6529739499092102,
        0.7573803663253784
      ]
    },
    {
      "coordinates": [
        273,
        153
      ],
      "magnitude": 1.0070116519927979,
      "direction": [
        0.9396117329597473,
        0.3422422409057617
      ]
    },
    {
      "coordinates": [
        296,
        153
      ],
      "magnitude": 0.9786416292190552,
      "direction": [
        0.9593991637229919,
        0.2820517122745514
      ]
    },
    {
      "coordinates": [
        319,
        153
      ],
      "magnitude": 1.1613460779190063,
      "direction": [
        0.9868853688240051,
        0.16142334043979645
      ]
    },
    {
      "coordinates": [
        0,
        170
      ],
      "magnitude": 1.5705828666687012,
      "direction": [
        0.258043497800827,
        0.9661332964897156
      ]
    },
    {
      "coordinates": [
        22,
        170
      ],
      "magnitude": 1.6394824981689453,
      "direction": [
        0.22187362611293793,
        0.975075364112854
      ]
    },
    {
      "coordinates": [
        45,
        170
      ],
      "magnitude": 2.00419545173645,
      "direction": [
        0.27070173621177673,
        0.9626632928848267
      ]
    },
    {
      "coordinates": [
        68,
        170
      ],
      "magnitude": 2.2282962799072266,
      "direction": [
        0.3303349018096924,
        0.9438637495040894
      ]
    },
    {
      "coordinates": [
        91,
        170
      ],
      "magnitude": 1.934227705001831,
      "direction": [
        0.4289821684360504,
        0.9033129215240479
      ]
    },
    {
      "coordinates": [
        113,
        170
      ],
      "magnitude": 2.53603458404541,
      "direction": [
        0.44679784774780273,
        0.894635021686554
      ]
    },
    {
      "coordinates": [
        136,
        170
      ],
      "magnitude": 3.352773904800415,
      "direction": [
        0.4013298749923706,
        0.9159335494041443
      ]
    },
    {
      "coordinates": [
        159,
        170
      ],
      "magnitude": 3.8720264434814453,
      "direction": [
        0.28340959548950195,
        0.9589989185333252
      ]
    },
    {
      "coordinates": [
        182,
        170
      ],
      "magnitude": 3.925997734069824,
      "direction": [
        0.20439279079437256,
        0.9788889288902283
      ]
    },
    {
      "coordinates": [
        205,
        170
      ],
      "magnitude": 3.0511646270751953,
      "direction": [
        0.24297641217708588,
        0.9700322151184082
      ]
    },
    {
      "coordinates": [
        227,
        170
      ],
      "magnitude": 1.8797023296356201,
      "direction": [
        0.39308813214302063,
        0.9195008277893066
      ]
    },
    {
      "coordinates": [
        250,
        170
      ],
      "magnitude": 1.414046287536621,
      "direction": [
        0.7742066383361816,
        0.6329329013824463
      ]
    },
    {
      "coordinates": [
        273,
        170
      ],
      "magnitude": 1.1106035709381104,
      "direction": [
        0.908966064453125,
        0.41686996817588806
      ]
    },
    {
      "coordinates": [
        296,
        170
      ],
      "magnitude": 0.8309955596923828,
      "direction": [
        0.9852678179740906,
        0.17101885378360748
      ]
    },
    {
      "coordinates": [
        319,
        170
      ],
      "magnitude": 1.072993516921997,
      "direction": [
        0.9999899864196777,
        -0.004470882471650839
      ]
    },
    {
      "coordinates": [
        0,
        187
      ],
      "magnitude": 1.3446286916732788,
      "direction": [
        0.1029876321554184,
        0.9946826696395874
      ]
    },
    {
      "coordinates": [
        22,
        187
      ],
      "magnitude": 1.6377863883972168,
      "direction": [
        0.13145270943641663,
        0.99132239818573
      ]
    },
    {
      "coordinates": [
        45,
        187
      ],
      "magnitude": 1.784725308418274,
      "direction": [
        0.05309951305389404,
        0.9985892176628113
      ]
    },
    {
      "coordinates": [
        68,
        187
      ],
      "magnitude": 1.9687331914901733,
      "direction": [
        0.12599588930606842,
        0.9920307993888855
      ]
    },
    {
      "coordinates": [
        91,
        187
      ],
      "magnitude": 1.7510184049606323,
      "direction": [
        0.4834024906158447,
        0.8753982186317444
      ]
    },
    {
      "coordinates": [
        113,
        187
      ],
      "magnitude": 2.3815033435821533,
      "direction": [
        0.4324254095554352,
        0.9016696810722351
      ]
    },
    {
      "coordinates": [
        136,
        187
      ],
      "magnitude": 3.124302387237549,
      "direction": [
        0.32570159435272217,
        0.9454725980758667
      ]
    },
    {
      "coordinates": [
        159,
        187
      ],
      "magnitude": 3.906407356262207,
      "direction": [
        0.3268170952796936,
        0.9450876116752625
      ]
    },
    {
      "coordinates": [
        182,
        187
      ],
      "magnitude": 4.414858341217041,
      "direction": [
        0.2996078431606293,
        0.9540624022483826
      ]
    },
    {
      "coordinates": [
        205,
        187
      ],
      "magnitude": 3.1615383625030518,
      "direction": [
        0.34272804856300354,
        0.9394346475601196
      ]
    },
    {
      "coordinates": [
        227,
        187
      ],
      "magnitude": 2.0637049674987793,
      "direction": [
        0.5467808842658997,
        0.8372756838798523
      ]
    },
    {
      "coordinates": [
        250,
        187
      ],
      "magnitude": 1.3971190452575684,
      "direction": [
        0.7259584665298462,
        0.6877384781837463
      ]
    },
    {
      "coordinates": [
        273,
        187
      ],
      "magnitude": 1.1098679304122925,
      "direction": [
        0.8801420331001282,
        0.4747104346752167
      ]
    },
    {
      "coordinates": [
        296,
        187
      ],
      "magnitude": 1.1439062356948853,
      "direction": [
        0.9919357299804688,
        0.1267417073249817
      ]
    },
    {
      "coordinates": [
        319,
        187
      ],
      "magnitude": 1.3735774755477905,
      "direction": [
        0.9701877236366272,
        -0.24235482513904572
      ]
    },
    {
      "coordinates": [
        0,
        204
      ],
      "magnitude": 1.1289340257644653,
      "direction": [
        -0.18628878891468048,
        0.9824950695037842
      ]
    },
    {
      "coordinates": [
        22,
        204
      ],
      "magnitude": 1.6437634229660034,
      "direction": [
        -0.18436384201049805,
        0.9828580617904663
      ]
    },
    {
      "coordinates": [
        45,
        204
      ],
      "magnitude": 1.9428695440292358,
      "direction": [
        -0.269600510597229,
        0.9629722833633423
      ]
    },
    {
      "coordinates": [
        68,
        204
      ],
      "magnitude": 1.5700546503067017,
      "direction": [
        0.008688786067068577,
        0.9999622106552124
      ]
    },
    {
      "coordinates": [
        91,
        204
      ],
      "magnitude": 1.3137096166610718,
      "direction": [
        0.25570613145828247,
        0.9667545557022095
      ]
    },
    {
      "coordinates": [
        113,
        204
      ],
      "magnitude": 2.3519792556762695,
      "direction": [
        0.2443578541278839,
        0.9696850776672363
      ]
    },
    {
      "coordinates": [
        136,
        204
      ],
      "magnitude": 2.848632335662842,
      "direction": [
        0.3940426707267761,
        0.9190921187400818
      ]
    },
    {
      "coordinates": [
        159,
        204
      ],
      "magnitude": 3.5778555870056152,
      "direction": [
        0.3400198221206665,
        0.9404182434082031
      ]
    },
    {
      "coordinates": [
        182,
        204
      ],
      "magnitude": 4.79968786239624,
      "direction": [
        0.27024516463279724,
        0.9627915620803833
      ]
    },
    {
      "coordinates": [
        205,
        204
      ],
      "magnitude": 3.1616930961608887,
      "direction": [
        0.44649404287338257,
        0.8947865962982178
      ]
    },
    {
      "coordinates": [
        227,
        204
      ],
      "magnitude": 2.1270194053649902,
      "direction": [
        0.6959908604621887,
        0.7180507183074951
      ]
    },
    {
      "coordinates": [
        250,
        204
      ],
      "magnitude": 1.613870620727539,
      "direction": [
        0.7589040994644165,
        0.651202380657196
      ]
    },
    {
      "coordinates": [
        273,
        204
      ],
      "magnitude": 1.416440486907959,
      "direction": [
        0.933841347694397,
        0.35768741369247437
      ]
    },
    {
      "coordinates": [
        296,
        204
      ],
      "magnitude": 1.3050860166549683,
      "direction": [
        0.9999986290931702,
        -0.0016438678139820695
      ]
    },
    {
      "coordinates": [
        319,
        204
      ],
      "magnitude": 1.5719038248062134,
      "direction": [
        0.945574164390564,
        -0.32540664076805115
      ]
    },
    {
      "coordinates": [
        0,
        221
      ],
      "magnitude": 1.3437399864196777,
      "direction": [
        -0.44565120339393616,
        0.89520663022995
      ]
    },
    {
      "coordinates": [
        22,
        221
      ],
      "magnitude": 1.8047794103622437,
      "direction": [
        -0.35923802852630615,
        0.9332460165023804
      ]
    },
    {
      "coordinates": [
        45,
        221
      ],
      "magnitude": 1.5753657817840576,
      "direction": [
        -0.15391843020915985,
        0.9880836009979248
      ]
    },
    {
      "coordinates": [
        68,
        221
      ],
      "magnitude": 1.175709843635559,
      "direction": [
        -0.08629045635461807,
        0.9962700605392456
      ]
    },
    {
      "coordinates": [
        91,
        221
      ],
      "magnitude": 1.1887773275375366,
      "direction": [
        0.021576929837465286,
        0.9997671246528625
      ]
    },
    {
      "coordinates": [
        113,
        221
      ],
      "magnitude": 1.8303167819976807,
      "direction": [
        0.3392865061759949,
        0.9406830668449402
      ]
    },
    {
      "coordinates": [
        136,
        221
      ],
      "magnitude": 2.8977699279785156,
      "direction": [
        0.5115967392921448,
        0.8592256903648376
      ]
    },
    {
      "coordinates": [
        159,
        221
      ],
      "magnitude": 3.8537707328796387,
      "direction": [
        0.39448755979537964,
        0.9189013242721558
      ]
    },
    {
      "coordinates": [
        182,
        221
      ],
      "magnitude": 4.292054176330566,
      "direction": [
        0.30420804023742676,
        0.9526056051254272
      ]
    },
    {
      "coordinates": [
        205,
        221
      ],
      "magnitude": 3.2703347206115723,
      "direction": [
        0.5767304301261902,
        0.8169345855712891
      ]
    },
    {
      "coordinates": [
        227,
        221
      ],
      "magnitude": 2.5793144702911377,
      "direction": [
        0.7429512739181519,
        0.6693454384803772
      ]
    },
    {
      "coordinates": [
        250,
        221
      ],
      "magnitude": 2.218427896499634,
      "direction": [
        0.8489616513252258,
        0.5284545421600342
      ]
    },
    {
      "coordinates": [
        273,
        221
      ],
      "magnitude": 1.9699745178222656,
      "direction": [
        0.9646619558334351,
        0.2634904980659485
      ]
    },
    {
      "coordinates": [
        296,
        221
      ],
      "magnitude": 1.5817193984985352,
      "direction": [
        0.9972454309463501,
        0.07417265325784683
      ]
    },
    {
      "coordinates": [
        319,
        221
      ],
      "magnitude": 1.488111972808838,
      "direction": [
        0.9314742088317871,
        -0.3638072609901428
      ]
    },
    {
      "coordinates": [
        0,
        239
      ],
      "magnitude": 1.710489273071289,
      "direction": [
        -0.4942874610424042,
        0.86929851770401
      ]
    },
    {
      "coordinates": [
        22,
        239
      ],
      "magnitude": 1.8823230266571045,
      "direction": [
        -0.4895608127117157,
        0.8719691634178162
      ]
    },
    {
      "coordinates": [
        45,
        239
      ],
      "magnitude": 1.5719350576400757,
      "direction": [
        -0.449408620595932,
        0.8933262825012207
      ]
    },
    {
      "coordinates": [
        68,
        239
      ],
      "magnitude": 1.2578963041305542,
      "direction": [
        -0.41344961524009705,
        0.9105269908905029
      ]
    },
    {
      "coordinates": [
        91,
        239
      ],
      "magnitude": 0.997685968875885,
      "direction": [
        0.12034516781568527,
        0.9927321076393127
      ]
    },
    {
      "coordinates": [
        113,
        239
      ],
      "magnitude": 1.1195961236953735,
      "direction": [
        0.6547390818595886,
        0.7558550238609314
      ]
    },
    {
      "coordinates": [
        136,
        239
      ],
      "magnitude": 3.096298933029175,
      "direction": [
        0.6261245608329773,
        0.779723048210144
      ]
    },
    {
      "coordinates": [
        159,
        239
      ],
      "magnitude": 3.905600070953369,
      "direction": [
        0.40035292506217957,
        0.9163610339164734
      ]
    },
    {
      "coordinates": [
        182,
        239
      ],
      "magnitude": 4.081326484680176,
      "direction": [
        0.43210461735725403,
        0.9018234610557556
      ]
    },
    {
      "coordinates": [
        205,
        239
      ],
      "magnitude": 3.5251524448394775,
      "direction": [
        0.6583724617958069,
        0.7526922821998596
      ]
    },
    {
      "coordinates": [
        227,
        239
      ],
      "magnitude": 3.07729172706604,
      "direction": [
        0.7780124545097351,
        0.6282488703727722
      ]
    },
    {
      "coordinates": [
        250,
        239
      ],
      "magnitude": 2.496584177017212,
      "direction": [
        0.8783180117607117,
        0.4780767858028412
      ]
    },
    {
      "coordinates": [
        273,
        239
      ],
      "magnitude": 2.2357470989227295,
      "direction": [
        0.9674444794654846,
        0.2530830502510071
      ]
    },
    {
      "coordinates": [
        296,
        239
      ],
      "magnitude": 1.9252923727035522,
      "direction": [
        0.9805313348770142,
        0.19636277854442596
      ]
    },
    {
      "coordinates": [
        319,
        239
      ],
      "magnitude": 1.5758394002914429,
      "direction": [
        0.952418327331543,
        -0.30479398369789124
      ]
    }
  ]
}